medium_muncher/__init__.py
medium_muncher/medium_muncher.py
mediumMuncher-0.2.0.dist-info/METADATA
mediumMuncher-0.2.0.dist-info/WHEEL
mediumMuncher-0.2.0.dist-info/top_level.txt
mediumMuncher-0.2.0.dist-info/RECORD
