Metadata-Version: 2.1
Name: mediumMuncher
Version: 0.2.0
Summary: UNKNOWN
Home-page: https://github.com/norton120/mediumMuncher
Author: Ethan Knox
License: MIT
Keywords: Medium
Platform: UNKNOWN
Requires-Dist: requests (==2.22.0)
